APS/Sem_1/Budsky_Matyas_CPU.v
`default_nettype none
module processor( input         clk, reset,
                  output [31:0] PC,
                  input  [31:0] instruction,
                  output        WE,
                  output [31:0] address_to_mem,
                  output [31:0] data_to_mem,
                  input  [31:0] data_from_mem
                );
	// declare wiring			
    wire [31:0] rs1, rs2, ALUOut, ImmOp, srcB, BranchTarget, BrTargetSrc, PCn, PCPlus4, res, BrJalxMuxOut;
	wire BranchBeq, BranchBlt, BranchJal, BranchJalr, BranchAuiPC,
		 RegWrite, MemWrite,
		 Zero, Lst,
		 BranchOutcome, ALUSrc, BrTargetSelect, BranchJalx, MemToReg;
	wire [3:0] immControl, ALUControl;

	assign WE = MemWrite;
	assign data_to_mem = rs2;
	assign address_to_mem = ALUOut; 	 
	

	// declare main cpu components
	PC_reg PCReg1 (PCn, clk, reset, PC);
	register_file registerFile1(instruction[19:15], instruction[24:20], instruction[11:7],
								 clk, RegWrite, reset, res, rs1, rs2 );

	imm_control immDecoder1(instruction[31:7], immControl, ImmOp);

	ALU ALU1(rs1, srcB, ALUControl, Zero, Lst, ALUOut);

	control_unit controlUnit1( 
					instruction,
					BranchBeq,
		     	    BranchBlt,
		     	    BranchJal,
		     	    BranchJalr,
					BranchAuiPC,
		     	    RegWrite,
		     	    MemToReg,
		     	    MemWrite,
					ALUControl,
					ALUSrc,
					immControl);

	// declare multiplexors
	mux_2_1 mux_BrOutcome (PCPlus4, BranchTarget, BranchOutcome, PCn);
	mux_2_1 mux_ALUSrc (rs2, ImmOp, ALUSrc, srcB);
	mux_2_1 mux_BrTarget (BrTargetSrc, ALUOut, BrTargetSelect, BranchTarget);
	mux_2_1 mux_BrJalx (ALUOut, PCPlus4, BranchJalx, BrJalxMuxOut);
	mux_2_1 mux_MemToReg (BrJalxMuxOut, data_from_mem, MemToReg, res);

	// declare adders
	adder_32bit adder_PC4 (4, PC, PCPlus4);
	adder_32bit adder_PCImm (ImmOp, PC, BrTargetSrc);

	// adittional logic gates for resolving branching
	assign BranchJalx = BranchJal || BranchJalr;
	assign BrTargetSelect = BranchJalr || BranchAuiPC;
	assign BranchOutcome = BranchJalx || BrTargetSelect || (BranchBeq && Zero) || (BranchBlt && Lst);
	

endmodule

module PC_reg(  input [31:0] PCn,
				input clk, reset,
			    output [31:0] PC
			);
	reg [31:0] PCregister;

	assign PC = PCregister;
	always @ (posedge clk) begin
		PCregister = PCn;
		if (reset) PCregister = 0;
	end
		
	
endmodule

module adder_32bit( input [31:0] num1, num2,
	      	    output [31:0] sum
	    	  ); 	  
	assign sum = num1 + num2;
endmodule



module mux_2_1( input [31:0] in0, in1,
		input select,
		output [31:0] out
	      );
	assign out = select?in1:in0;
endmodule
	 

module register_file( input [4:0] a1, a2, a3,
		      input clk, we3, reset,
		      input [31:0] wd3,
		      output [31:0] rd1, rd2
		    );  
	reg [31:0] rf[31:0];
	
	always @ (reset) rf[0] = 0;

	assign rd1 = rf[a1];
	assign rd2 = rf[a2];
	
	always @ (posedge clk) begin
		if(we3 && a3 != 0) rf[a3] = wd3;
	end		
endmodule

// I - 0, S - 1, B - 2, U - 3 (upper immediate), J - 4
module imm_control( input [24:0] instruction,
		    input [3:0] immControl,
		    output reg [31:0] out
		  );
	always @(*) begin
		case(immControl)
			// I-type
			0:begin
				out[10:0] = instruction[23:13];
				out[31:11] = instruction[24];
			  end
			// S-type  
			1:begin
				out[4:0] = instruction[4:0];
				out[10:5] = instruction[23:18];
				out[31:11] = instruction[24];
			  end  
			// B-type
			2:begin
				out[0] = 0;
				out[4:1] = instruction[4:1];
				out[10:5] = instruction[23:18];
				out[11] = instruction[0];
				out[31:12] = instruction[24];
			  end   
			// U-type
			3:begin
				out[11:0] = 0;
				out[31:12] = instruction[24:5];
			  end
			// J-type
			4:begin
				out[0] = 0;
				out[10:1] = instruction[23:12];
				out[11] = instruction[11];
				out[19:12] = instruction[10:5];
				out[31:20] = instruction[24];

			end

		endcase
	end
		  
endmodule

// add - 0, and - 1, sub - 2, slt - 3, div - 4, rem - 5, sll - 6, srl - 7, sra - 8, lui - 9
module ALU( input [31:0] srcA, srcB,
	    input [3:0] ALUControl,
	    output reg Zero, LesserThan,
	    output reg [31:0] ALUOut
	  );
	always @(*) begin
		case(ALUControl)
			0: ALUOut = srcA + srcB;
			1: ALUOut = srcA & srcB;
			2: ALUOut = srcA - srcB;
			3:begin
				ALUOut[0] = srcA < srcB;
				ALUOut[31:1] = 0;
				if( ALUOut[0] )
					LesserThan = 1;
				else
					LesserThan = 0;	
			  end	
			4: ALUOut = srcA / srcB;
			5: ALUOut = srcA % srcB;
			6: ALUOut = srcA << srcB;
			7: ALUOut = srcA >> srcB;
			8: ALUOut = srcA >>> srcB;
			9: ALUOut = srcB;
		endcase
	end
	
	always @(ALUOut) begin
		if(ALUOut == 0) Zero = 1;
		else Zero = 0;
	end

endmodule


module control_unit( input [31:0] instruction,
		     output reg BranchBeq,
		     	    BranchBlt,
		     	    BranchJal,
		     	    BranchJalr,
					BranchAuiPC,
		     	    RegWrite,
		     	    MemToReg,
		     	    MemWrite,
		     output reg [3:0] ALUControl,
		     output reg ALUSrc,
		     output reg [3:0] immControl
		   );
	always @(*) begin
		case(instruction[6:0])
			// all ALU reliant operations without immediate
			51:begin
				BranchBeq = 0;
				BranchBlt = 0;
				BranchJal = 0;
				BranchJalr = 0;
				BranchAuiPC = 0;
				RegWrite = 1;
				MemToReg = 0;
				MemWrite = 0;
				ALUSrc = 0;
				case(instruction[14:12])
					0:begin
						case(instruction[31:25])
							// add
							0: ALUControl = 0;
							// sub
							32: ALUControl = 2;
						endcase
					end
					// and
					7: ALUControl = 1;
					// slt
					2: ALUControl = 3;
					// div
					4: ALUControl = 4;
					// rem
					6: ALUControl = 5;
					// sll
					1: ALUControl = 6;
					
					// right shifts
					5:begin
						case(instruction[31:25])
							// srl
							0: ALUControl = 7;
							// sra
							32: ALUControl = 8;
						endcase
					end
				endcase
			end
			
			// addi
			19:begin
				BranchBeq = 0;
				BranchBlt = 0;
				BranchAuiPC = 0;
     	    	BranchJal = 0;
     	    	BranchJalr = 0;
     	    	RegWrite = 1;
		     	MemToReg = 0;
		     	MemWrite = 0;
				ALUControl = 0;
				immControl = 0;
				ALUSrc = 1;
			end
			
			// branch operations
			99:begin
				BranchJal = 0;
				BranchJalr = 0;
				BranchAuiPC = 0;				
				RegWrite = 0;
				MemToReg = 0;
				MemWrite = 0;
				immControl = 2;
				ALUSrc = 0;
				case(instruction[14:12])
					// beq
					0:begin
						BranchBeq = 1;
						BranchBlt = 0;
						ALUControl = 2;
					end
					
					// blt
					4:begin
						BranchBeq = 0;
						BranchBlt = 1;
						ALUControl = 3;
					end
				endcase	
			end
			
			// lw
			3:begin
				BranchBeq = 0;
				BranchBlt = 0;
				BranchJal = 0;
				BranchJalr = 0;
				BranchAuiPC = 0;
				RegWrite = 1;
				MemToReg = 1;
				MemWrite = 0;
				ALUControl = 0;
				immControl = 0;
				ALUSrc = 1;
			end
			
			// sw
			35:begin
				BranchBeq = 0;
				BranchBlt = 0;
				BranchJal = 0;
				BranchJalr = 0;
				BranchAuiPC = 0;
				RegWrite = 0;
				MemToReg = 0;
				MemWrite = 1;
				ALUControl = 0;
				immControl = 1;
				ALUSrc = 1;
			end
			
			// lui
			55:begin
				BranchBeq = 0;
				BranchBlt = 0;
				BranchJal = 0;
				BranchJalr = 0;
				BranchAuiPC = 0;
				RegWrite = 1;
				MemToReg = 0;
				MemWrite = 0;
				ALUControl = 9;
				immControl = 3;
				ALUSrc = 1;
			end
			
			// jal
			111:begin
				BranchBeq = 0;
				BranchBlt = 0;
				BranchJal = 1;
				BranchJalr = 0;
				BranchAuiPC = 0;
				RegWrite = 1;
				MemToReg = 0;
				MemWrite = 0;
				immControl = 4;
			end
			
			// jalr
			103:begin
				BranchBeq = 0;
				BranchBlt = 0;
				BranchJal = 0;
				BranchJalr = 1;
				BranchAuiPC = 0;
				RegWrite = 1;
				MemToReg = 0;
				MemWrite = 0;
				ALUControl = 0;
				immControl = 0;
				ALUSrc = 1;
			end
			
			// auipc
			23:begin
				BranchBeq = 0;
				BranchBlt = 0;
				BranchJal = 0;
				BranchJalr = 0;
				BranchAuiPC = 1;
				RegWrite = 0;
				MemToReg = 0;
				MemWrite = 0;
				immControl = 3;
				ALUSrc = 1;
			end
			    
		endcase
	end
endmodule
`default_nettype wire

APS/Sem_1/additional_modules.v
module top (	input         clk, reset,
		output [31:0] data_to_mem, address_to_mem,
		output        write_enable);

	wire [31:0] pc, instruction, data_from_mem;

	inst_mem  imem(pc[7:2], instruction);
	data_mem  dmem(clk, write_enable, address_to_mem, data_to_mem, data_from_mem);
	processor CPU(clk, reset, pc, instruction, write_enable, address_to_mem, data_to_mem, data_from_mem);
endmodule

//-------------------------------------------------------------------
module data_mem (input clk, we,
		 input  [31:0] address, wd,
		 output [31:0] rd);

	reg [31:0] RAM[63:0];

	initial begin
		$readmemh ("memfile_data.hex",RAM,0,63);
	end

	assign rd=RAM[address[31:2]]; // word aligned

	always @ (posedge clk)
		if (we)
			RAM[address[31:2]]<=wd;
endmodule

//-------------------------------------------------------------------
module inst_mem (input  [5:0]  address,
		 output [31:0] rd);

	reg [31:0] RAM[127:0];
	initial begin
		$readmemh ("memfile_inst.hex",RAM,0,127);
	end
	assign rd=RAM[address]; // word aligned
endmodule

APS/Sem_1/testbenches/testbench.v
module testbench();
	reg         clk;
	reg         reset;
	wire [31:0] data_to_mem, address_to_mem;
	wire        write_enable;

	top simulated_system (clk, reset, data_to_mem, address_to_mem, write_enable);

	initial	begin
		$dumpfile("tb_asm_alu");
		$dumpvars;
		reset<=1; # 2; reset<=0;
		#100;
		$writememh ("memfile_data_after_simulation.hex",simulated_system.dmem.RAM,0,63);
		$finish;
	end

	// generate clock
	always	begin
		clk<=1; # 1; clk<=0; # 1;
	end
endmodule

APS/Sem_1/tb_asm_alu.vcd
$date
	Wed Nov 15 19:22:01 2023
$end
$version
	Icarus Verilog
$end
$timescale
	1s
$end
$scope module testbench $end
$var wire 1 ! write_enable $end
$var wire 32 " data_to_mem [31:0] $end
$var wire 32 # address_to_mem [31:0] $end
$var reg 1 $ clk $end
$var reg 1 % reset $end
$scope module simulated_system $end
$var wire 1 $ clk $end
$var wire 1 % reset $end
$var wire 1 ! write_enable $end
$var wire 32 & pc [31:0] $end
$var wire 32 ' instruction [31:0] $end
$var wire 32 ( data_to_mem [31:0] $end
$var wire 32 ) data_from_mem [31:0] $end
$var wire 32 * address_to_mem [31:0] $end
$scope module CPU $end
$var wire 1 + BrTargetSelect $end
$var wire 1 , BranchJalx $end
$var wire 1 - BranchOutcome $end
$var wire 1 ! WE $end
$var wire 32 . address_to_mem [31:0] $end
$var wire 1 $ clk $end
$var wire 32 / data_to_mem [31:0] $end
$var wire 1 % reset $end
$var wire 32 0 srcB [31:0] $end
$var wire 32 1 rs2 [31:0] $end
$var wire 32 2 rs1 [31:0] $end
$var wire 32 3 res [31:0] $end
$var wire 32 4 instruction [31:0] $end
$var wire 4 5 immControl [3:0] $end
$var wire 32 6 data_from_mem [31:0] $end
$var wire 1 7 Zero $end
$var wire 1 8 RegWrite $end
$var wire 32 9 PCn [31:0] $end
$var wire 32 : PCPlus4 [31:0] $end
$var wire 32 ; PC [31:0] $end
$var wire 1 < MemWrite $end
$var wire 1 = MemToReg $end
$var wire 1 > Lst $end
$var wire 32 ? ImmOp [31:0] $end
$var wire 32 @ BranchTarget [31:0] $end
$var wire 1 A BranchJalr $end
$var wire 1 B BranchJal $end
$var wire 1 C BranchBlt $end
$var wire 1 D BranchBeq $end
$var wire 1 E BranchAuiPC $end
$var wire 32 F BrTargetSrc [31:0] $end
$var wire 32 G BrJalxMuxOut [31:0] $end
$var wire 1 H ALUSrc $end
$var wire 32 I ALUOut [31:0] $end
$var wire 4 J ALUControl [3:0] $end
$scope module ALU1 $end
$var wire 32 K srcB [31:0] $end
$var wire 32 L srcA [31:0] $end
$var wire 4 M ALUControl [3:0] $end
$var reg 32 N ALUOut [31:0] $end
$var reg 1 > LesserThan $end
$var reg 1 7 Zero $end
$upscope $end
$scope module PCReg1 $end
$var wire 1 $ clk $end
$var wire 1 % reset $end
$var wire 32 O PCn [31:0] $end
$var wire 32 P PC [31:0] $end
$var reg 32 Q PCregister [31:0] $end
$upscope $end
$scope module adder_PC4 $end
$var wire 32 R num1 [31:0] $end
$var wire 32 S num2 [31:0] $end
$var wire 32 T sum [31:0] $end
$upscope $end
$scope module adder_PCImm $end
$var wire 32 U num2 [31:0] $end
$var wire 32 V sum [31:0] $end
$var wire 32 W num1 [31:0] $end
$upscope $end
$scope module controlUnit1 $end
$var wire 32 X instruction [31:0] $end
$var reg 4 Y ALUControl [3:0] $end
$var reg 1 H ALUSrc $end
$var reg 1 E BranchAuiPC $end
$var reg 1 D BranchBeq $end
$var reg 1 C BranchBlt $end
$var reg 1 B BranchJal $end
$var reg 1 A BranchJalr $end
$var reg 1 = MemToReg $end
$var reg 1 < MemWrite $end
$var reg 1 8 RegWrite $end
$var reg 4 Z immControl [3:0] $end
$upscope $end
$scope module immDecoder1 $end
$var wire 4 [ immControl [3:0] $end
$var wire 25 \ instruction [24:0] $end
$var reg 32 ] out [31:0] $end
$upscope $end
$scope module mux_ALUSrc $end
$var wire 32 ^ in1 [31:0] $end
$var wire 1 H select $end
$var wire 32 _ out [31:0] $end
$var wire 32 ` in0 [31:0] $end
$upscope $end
$scope module mux_BrJalx $end
$var wire 32 a in0 [31:0] $end
$var wire 32 b in1 [31:0] $end
$var wire 1 , select $end
$var wire 32 c out [31:0] $end
$upscope $end
$scope module mux_BrOutcome $end
$var wire 32 d in0 [31:0] $end
$var wire 1 - select $end
$var wire 32 e out [31:0] $end
$var wire 32 f in1 [31:0] $end
$upscope $end
$scope module mux_BrTarget $end
$var wire 32 g in0 [31:0] $end
$var wire 32 h in1 [31:0] $end
$var wire 1 + select $end
$var wire 32 i out [31:0] $end
$upscope $end
$scope module mux_MemToReg $end
$var wire 32 j in0 [31:0] $end
$var wire 1 = select $end
$var wire 32 k out [31:0] $end
$var wire 32 l in1 [31:0] $end
$upscope $end
$scope module registerFile1 $end
$var wire 5 m a1 [4:0] $end
$var wire 5 n a2 [4:0] $end
$var wire 5 o a3 [4:0] $end
$var wire 1 $ clk $end
$var wire 32 p rd1 [31:0] $end
$var wire 32 q rd2 [31:0] $end
$var wire 1 % reset $end
$var wire 32 r wd3 [31:0] $end
$var wire 1 8 we3 $end
$upscope $end
$upscope $end
$scope module dmem $end
$var wire 32 s address [31:0] $end
$var wire 1 $ clk $end
$var wire 32 t rd [31:0] $end
$var wire 32 u wd [31:0] $end
$var wire 1 ! we $end
$upscope $end
$scope module imem $end
$var wire 6 v address [5:0] $end
$var wire 32 w rd [31:0] $end
$upscope $end
$upscope $end
$upscope $end
$enddefinitions $end
#0
$dumpvars
b100000000000000010010011 w
b0 v
bx u
b0 t
b1000 s
b1000 r
bx q
b0 p
b1 o
b1000 n
b0 m
b0 l
b1000 k
b1000 j
b1000 i
b1000 h
b1000 g
b1000 f
b100 e
b100 d
b1000 c
b100 b
b1000 a
bx `
b1000 _
b1000 ^
b1000 ]
b10000000000000001 \
b0 [
b0 Z
b0 Y
b100000000000000010010011 X
b1000 W
b1000 V
b0 U
b100 T
b0 S
b100 R
b0 Q
b0 P
b100 O
b1000 N
b0 M
b0 L
b1000 K
b0 J
b1000 I
1H
b1000 G
b1000 F
0E
0D
0C
0B
0A
b1000 @
b1000 ?
x>
0=
0<
b0 ;
b100 :
b100 9
18
07
b0 6
b0 5
b100000000000000010010011 4
b1000 3
b0 2
bx 1
b1000 0
bx /
b1000 .
0-
0,
0+
b1000 *
b0 )
bx (
b100000000000000010010011 '
b0 &
1%
1$
b1000 #
bx "
0!
$end
#1
0$
#2
b110 3
b110 k
b110 r
b110 G
b110 c
b110 j
b110 #
b110 *
b110 .
b110 s
b110 I
b110 N
b110 a
b110 h
b110 0
b110 K
b110 _
b110 ?
b110 W
b110 ]
b110 ^
b1100000000000010 \
b10 o
b110 n
b1000 9
b1000 O
b1000 e
b1010 @
b1010 f
b1010 i
b11000000000000100010011 '
b11000000000000100010011 4
b11000000000000100010011 X
b11000000000000100010011 w
b1 v
b1000 :
b1000 T
b1000 b
b1000 d
b1010 F
b1010 V
b1010 g
b100 &
b100 ;
b100 P
b100 Q
b100 S
b100 U
1$
0%
#3
0$
#4
b1000 3
b1000 k
b1000 r
b1000 G
b1000 c
b1000 j
b1000 #
b1000 *
b1000 .
b1000 s
b1000 I
b1000 N
b1000 a
b1000 h
b1000 0
b1000 K
b1000 _
b1000 ?
b1000 W
b1000 ]
b1000 ^
b10000000000000101 \
b101 o
b1000 n
b1100 9
b1100 O
b1100 e
b10000 @
b10000 f
b10000 i
b100000000000001010010011 '
b100000000000001010010011 4
b100000000000001010010011 X
b100000000000001010010011 w
b10 v
b1100 :
b1100 T
b1100 b
b1100 d
b10000 F
b10000 V
b10000 g
b1000 &
b1000 ;
b1000 P
b1000 Q
b1000 S
b1000 U
1$
#5
0$
#6
b10 3
b10 k
b10 r
b10 G
b10 c
b10 j
b10 #
b10 *
b10 .
b10 s
b10 I
b10 N
b10 a
b10 h
b10 0
b10 K
b10 _
b10 ?
b10 W
b10 ]
b10 ^
b100000000000110 \
b110 o
b110 "
b110 (
b110 /
b110 u
b110 1
b110 `
b110 q
b10 n
b10000 9
b10000 O
b10000 e
b1110 @
b1110 f
b1110 i
b1000000000001100010011 '
b1000000000001100010011 4
b1000000000001100010011 X
b1000000000001100010011 w
b11 v
b10000 :
b10000 T
b10000 b
b10000 d
b1110 F
b1110 V
b1110 g
b1100 &
b1100 ;
b1100 P
b1100 Q
b1100 S
b1100 U
1$
#7
0$
#8
b1 3
b1 k
b1 r
b1 G
b1 c
b1 j
b1 #
b1 *
b1 .
b1 s
b1 I
b1 N
b1 a
b1 h
b1 0
b1 K
b1 _
b1 ?
b1 W
b1 ]
b1 ^
b10000000000111 \
b111 o
b1000 "
b1000 (
b1000 /
b1000 u
b1000 1
b1000 `
b1000 q
b1 n
b10100 9
b10100 O
b10100 e
b10001 @
b10001 f
b10001 i
b100000000001110010011 '
b100000000001110010011 4
b100000000001110010011 X
b100000000001110010011 w
b100 v
b10100 :
b10100 T
b10100 b
b10100 d
b10001 F
b10001 V
b10001 g
b10000 &
b10000 ;
b10000 P
b10000 Q
b10000 S
b10000 U
1$
#9
0$
#10
b1110 3
b1110 k
b1110 r
b1110 G
b1110 c
b1110 j
b10 ?
b10 W
b10 ]
b10 ^
b1110 #
b1110 *
b1110 .
b1110 s
b1110 I
b1110 N
b1110 a
b1110 h
b110 0
b110 K
b110 _
b100000100000011 \
b11 o
b110 "
b110 (
b110 /
b110 u
b110 1
b110 `
b110 q
b10 n
b1000 2
b1000 L
b1000 p
b1 m
0H
b11000 9
b11000 O
b11000 e
b10110 @
b10110 f
b10110 i
b1000001000000110110011 '
b1000001000000110110011 4
b1000001000000110110011 X
b1000001000000110110011 w
b101 v
b11000 :
b11000 T
b11000 b
b11000 d
b10110 F
b10110 V
b10110 g
b10100 &
b10100 ;
b10100 P
b10100 Q
b10100 S
b10100 U
1$
#11
0$
#12
b100 3
b100 k
b100 r
b100 G
b100 c
b100 j
b100 #
b100 *
b100 .
b100 s
b100 I
b100 N
b100 a
b100 h
b100 0
b100 K
b100 _
b100 ?
b100 W
b100 ]
b100 ^
b110000001000100 \
b100 o
b1110 "
b1110 (
b1110 /
b1110 u
b1110 1
b1110 `
b1110 q
b11 n
b0 2
b0 L
b0 p
b0 m
1H
b1 5
b1 Z
b1 [
1!
1<
08
b11100 9
b11100 O
b11100 e
b11100 @
b11100 f
b11100 i
b1100000010001000100011 '
b1100000010001000100011 4
b1100000010001000100011 X
b1100000010001000100011 w
b110 v
b11100 :
b11100 T
b11100 b
b11100 d
b11100 F
b11100 V
b11100 g
b11000 &
b11000 ;
b11000 P
b11000 Q
b11000 S
b11000 U
1$
#13
0$
#14
b10 3
b10 k
b10 r
b10 G
b10 c
b10 j
b10000000011 ?
b10000000011 W
b10000000011 ]
b10000000011 ^
b10 #
b10 *
b10 .
b10 s
b10 I
b10 N
b10 a
b10 h
b110 0
b110 K
b110 _
b100000000100000100000011 \
b11 o
b110 "
b110 (
b110 /
b110 u
b110 1
b110 `
b110 q
b10 n
b1000 2
b1000 L
b1000 p
b1 m
b10 J
b10 M
b10 Y
0H
0!
0<
18
b100000 9
b100000 O
b100000 e
b10000011111 @
b10000011111 f
b10000011111 i
b1000000001000001000000110110011 '
b1000000001000001000000110110011 4
b1000000001000001000000110110011 X
b1000000001000001000000110110011 w
b111 v
b100000 :
b100000 T
b100000 b
b100000 d
b10000011111 F
b10000011111 V
b10000011111 g
b11100 &
b11100 ;
b11100 P
b11100 Q
b11100 S
b11100 U
1$
#15
0$
#16
b1000 3
b1000 k
b1000 r
b1000 G
b1000 c
b1000 j
b0 )
b0 6
b0 l
b0 t
b1000 ?
b1000 W
b1000 ]
b1000 ^
b1000 0
b1000 K
b1000 _
b1000 #
b1000 *
b1000 .
b1000 s
b1000 I
b1000 N
b1000 a
b1000 h
b110000001001000 \
b1000 o
b10 "
b10 (
b10 /
b10 u
b10 1
b10 `
b10 q
b11 n
b0 2
b0 L
b0 p
b0 m
1H
b0 J
b0 M
b0 Y
1!
1<
08
b100100 9
b100100 O
b100100 e
b101000 @
b101000 f
b101000 i
b1100000010010000100011 '
b1100000010010000100011 4
b1100000010010000100011 X
b1100000010010000100011 w
b1000 v
b100100 :
b100100 T
b100100 b
b100100 d
b101000 F
b101000 V
b101000 g
b100000 &
b100000 ;
b100000 P
b100000 Q
b100000 S
b100000 U
1$
#17
0$
#18
b0 3
b0 k
b0 r
17
b0 G
b0 c
b0 j
b10000000011 ?
b10000000011 W
b10000000011 ]
b10000000011 ^
b0 #
b0 *
b0 .
b0 s
b0 I
b0 N
b0 a
b0 h
b100000001010000100000011 \
b11 o
b1000 "
b1000 (
b1000 /
b1000 u
b1000 1
b1000 `
b1000 q
b101 n
b1000 2
b1000 L
b1000 p
b1 m
b10 J
b10 M
b10 Y
0H
0!
0<
18
b101000 9
b101000 O
b101000 e
b10000100111 @
b10000100111 f
b10000100111 i
b1000000010100001000000110110011 '
b1000000010100001000000110110011 4
b1000000010100001000000110110011 X
b1000000010100001000000110110011 w
b1001 v
b101000 :
b101000 T
b101000 b
b101000 d
b10000100111 F
b10000100111 V
b10000100111 g
b100100 &
b100100 ;
b100100 P
b100100 Q
b100100 S
b100100 U
1$
#19
0$
#20
b1100 3
b1100 k
b1100 r
07
b1100 G
b1100 c
b1100 j
b0 )
b0 6
b0 l
b0 t
b1100 ?
b1100 W
b1100 ]
b1100 ^
b1100 0
b1100 K
b1100 _
b1100 #
b1100 *
b1100 .
b1100 s
b1100 I
b1100 N
b1100 a
b1100 h
b110000001001100 \
b1100 o
b0 "
b0 (
b0 /
b0 u
b0 1
b0 `
b0 q
b11 n
b0 2
b0 L
b0 p
b0 m
1H
b0 J
b0 M
b0 Y
1!
1<
08
b101100 9
b101100 O
b101100 e
b110100 @
b110100 f
b110100 i
b1100000010011000100011 '
b1100000010011000100011 4
b1100000010011000100011 X
b1100000010011000100011 w
b1010 v
b101100 :
b101100 T
b101100 b
b101100 d
b110100 F
b110100 V
b110100 g
b101000 &
b101000 ;
b101000 P
b101000 Q
b101000 S
b101000 U
1$
#21
0$
#22
b0 3
b0 k
b0 r
17
b0 G
b0 c
b0 j
b11 ?
b11 W
b11 ]
b11 ^
b0 #
b0 *
b0 .
b0 s
b0 I
b0 N
b0 a
b0 h
b110 0
b110 K
b110 _
b100000111100011 \
b11 o
b110 "
b110 (
b110 /
b110 u
b110 1
b110 `
b110 q
b10 n
b1000 2
b1000 L
b1000 p
b1 m
b1 J
b1 M
b1 Y
0H
0!
0<
18
b110000 9
b110000 O
b110000 e
b101111 @
b101111 f
b101111 i
b1000001111000110110011 '
b1000001111000110110011 4
b1000001111000110110011 X
b1000001111000110110011 w
b1011 v
b110000 :
b110000 T
b110000 b
b110000 d
b101111 F
b101111 V
b101111 g
b101100 &
b101100 ;
b101100 P
b101100 Q
b101100 S
b101100 U
1$
#23
0$
#24
b10000 3
b10000 k
b10000 r
07
b10000 G
b10000 c
b10000 j
b0 )
b0 6
b0 l
b0 t
b10000 ?
b10000 W
b10000 ]
b10000 ^
b10000 0
b10000 K
b10000 _
b10000 #
b10000 *
b10000 .
b10000 s
b10000 I
b10000 N
b10000 a
b10000 h
b110000001010000 \
b10000 o
b0 "
b0 (
b0 /
b0 u
b0 1
b0 `
b0 q
b11 n
b0 2
b0 L
b0 p
b0 m
1H
b0 J
b0 M
b0 Y
1!
1<
08
b110100 9
b110100 O
b110100 e
b1000000 @
b1000000 f
b1000000 i
b1100000010100000100011 '
b1100000010100000100011 4
b1100000010100000100011 X
b1100000010100000100011 w
b1100 v
b110100 :
b110100 T
b110100 b
b110100 d
b1000000 F
b1000000 V
b1000000 g
b110000 &
b110000 ;
b110000 P
b110000 Q
b110000 S
b110000 U
1$
#25
0$
#26
b0 3
b0 k
b0 r
17
b0 G
b0 c
b0 j
b100 ?
b100 W
b100 ]
b100 ^
0>
b0 #
b0 *
b0 .
b0 s
b0 I
b0 N
b0 a
b0 h
b110 0
b110 K
b110 _
b100000101000100 \
b100 o
b110 "
b110 (
b110 /
b110 u
b110 1
b110 `
b110 q
b10 n
b1000 2
b1000 L
b1000 p
b1 m
b11 J
b11 M
b11 Y
0H
0!
0<
18
b111000 9
b111000 O
b111000 e
b111000 @
b111000 f
b111000 i
b1000001010001000110011 '
b1000001010001000110011 4
b1000001010001000110011 X
b1000001010001000110011 w
b1101 v
b111000 :
b111000 T
b111000 b
b111000 d
b111000 F
b111000 V
b111000 g
b110100 &
b110100 ;
b110100 P
b110100 Q
b110100 S
b110100 U
1$
#27
0$
#28
b10100 3
b10100 k
b10100 r
07
b10100 G
b10100 c
b10100 j
b0 )
b0 6
b0 l
b0 t
b10100 ?
b10100 W
b10100 ]
b10100 ^
b10100 0
b10100 K
b10100 _
b10100 #
b10100 *
b10100 .
b10100 s
b10100 I
b10100 N
b10100 a
b10100 h
b1000000001010100 \
b10100 o
b0 "
b0 (
b0 /
b0 u
b0 1
b0 `
b0 q
b100 n
b0 2
b0 L
b0 p
b0 m
1H
b0 J
b0 M
b0 Y
1!
1<
08
b111100 9
b111100 O
b111100 e
b1001100 @
b1001100 f
b1001100 i
b10000000010101000100011 '
b10000000010101000100011 4
b10000000010101000100011 X
b10000000010101000100011 w
b1110 v
b111100 :
b111100 T
b111100 b
b111100 d
b1001100 F
b1001100 V
b1001100 g
b111000 &
b111000 ;
b111000 P
b111000 Q
b111000 S
b111000 U
1$
#29
0$
#30
b1 3
b1 k
b1 r
b1 G
b1 c
b1 j
b100 ?
b100 W
b100 ]
b100 ^
1>
b1 #
b1 *
b1 .
b1 s
b1 I
b1 N
b1 a
b1 h
b1000 0
b1000 K
b1000 _
b10001001000100 \
b100 o
b1000 "
b1000 (
b1000 /
b1000 u
b1000 1
b1000 `
b1000 q
b1 n
b110 2
b110 L
b110 p
b10 m
b11 J
b11 M
b11 Y
0H
0!
0<
18
b1000000 9
b1000000 O
b1000000 e
b1000000 @
b1000000 f
b1000000 i
b100010010001000110011 '
b100010010001000110011 4
b100010010001000110011 X
b100010010001000110011 w
b1111 v
b1000000 :
b1000000 T
b1000000 b
b1000000 d
b1000000 F
b1000000 V
b1000000 g
b111100 &
b111100 ;
b111100 P
b111100 Q
b111100 S
b111100 U
1$
#31
0$
#32
b11000 3
b11000 k
b11000 r
b11000 G
b11000 c
b11000 j
b0 )
b0 6
b0 l
b0 t
b11000 ?
b11000 W
b11000 ]
b11000 ^
b11000 0
b11000 K
b11000 _
b11000 #
b11000 *
b11000 .
b11000 s
b11000 I
b11000 N
b11000 a
b11000 h
b1000000001011000 \
b11000 o
b1 "
b1 (
b1 /
b1 u
b1 1
b1 `
b1 q
b100 n
b0 2
b0 L
b0 p
b0 m
1H
b0 J
b0 M
b0 Y
1!
1<
08
b1000100 9
b1000100 O
b1000100 e
b1011000 @
b1011000 f
b1011000 i
b10000000010110000100011 '
b10000000010110000100011 4
b10000000010110000100011 X
b10000000010110000100011 w
b10000 v
b1000100 :
b1000100 T
b1000100 b
b1000100 d
b1011000 F
b1011000 V
b1011000 g
b1000000 &
b1000000 ;
b1000000 P
b1000000 Q
b1000000 S
b1000000 U
1$
#33
0$
#34
b0 3
b0 k
b0 r
17
b0 G
b0 c
b0 j
b100 ?
b100 W
b100 ]
b100 ^
0>
b0 #
b0 *
b0 .
b0 s
b0 I
b0 N
b0 a
b0 h
b1000 0
b1000 K
b1000 _
b1010000101000100 \
b100 o
b1000 "
b1000 (
b1000 /
b1000 u
b1000 1
b1000 `
b1000 q
b101 n
b1000 2
b1000 L
b1000 p
b1 m
b11 J
b11 M
b11 Y
0H
0!
0<
18
b1001000 9
b1001000 O
b1001000 e
b1001000 @
b1001000 f
b1001000 i
b10100001010001000110011 '
b10100001010001000110011 4
b10100001010001000110011 X
b10100001010001000110011 w
b10001 v
b1001000 :
b1001000 T
b1001000 b
b1001000 d
b1001000 F
b1001000 V
b1001000 g
b1000100 &
b1000100 ;
b1000100 P
b1000100 Q
b1000100 S
b1000100 U
1$
#35
0$
